[{id: 0,
  institution: 0,
  availability: "nonexistent",
  name: "",
  description: "",
  privacyLevel: "public",
  boundary: null,
  baseMapSource: null,
  plotDistribution: "random",
  numPlots: null,
  plotSpacing: null,
  plotShape: "circle",
  plotSize: null,
  sampleDistribution: "random",
  samplesPerPlot: null,
  sampleResolution: null,
  sampleValues: [],
  archived: false},
  {id: 1,
    institution: 1,
    availability: "published",
    name: "Mekong River Region",
    description: "Laos, Cambodia, Vietnam, Thailand, Myanmar",
    privacyLevel: "public",
    boundary: "{\"type\":\"Polygon\",\"coordinates\":[[[95,10.5],[95,22.5],[107,22.5],[107,10.5],[95,10.5]]]}",
    baseMapSource: "DigitalGlobeRecentImagery+Streets",
    plotDistribution: "random",
    numPlots: 3,
    plotSpacing: null,
    plotShape: "circle",
    plotSize: 200,
    sampleDistribution: "random",
    samplesPerPlot: 15,
    sampleResolution: null,
    sampleValues: [{id: 1,
      name: "Land Use",
      values: [{color: "#1EC61B", name: "Forest", id: 1, image: null},
        {color: "#9CF135", name: "Grassland", id: 2, image: null},
        {color: "#D5DE85", name: "Bare Surface", id: 3, image: null},
        {color: "#8B9084", name: "Impervious Surface", id: 4, image: null},
        {color: "#F2C613", name: "Agriculture", id: 5, image: null},
        {color: "#6A3A75", name: "Urban", id: 6, image: null},
        {color: "#2F4DC0", name: "Water", id: 7, image: null},
        {color: "#FFFFFF", name: "Cloud", id: 8, image: null},
        {color: "#000000", name: "Unknown", id: 9, image: null}]}],
    archived: false},
  {id: 2,
    institution: 1,
    availability: "published",
    name: "California, USA",
    description: "The most populous state in the United States.",
    privacyLevel: "public",
    boundary: "{\"type\":\"Polygon\",\"coordinates\":[[[-124.6,32.3],[-124.6,42],[-114,42],[-114,32.3],[-124.6,32.3]]]}",
    baseMapSource: "DigitalGlobeRecentImagery+Streets",
    plotDistribution: "random",
    numPlots: 3,
    plotSpacing: null,
    plotShape: "circle",
    plotSize: 100,
    sampleDistribution: "random",
    samplesPerPlot: 5,
    sampleResolution: null,
    sampleValues: [{id: 1,
      name: "Land Use",
      values: [{color: null, name: "Rock/Sand", id: 10, image: null},
        {color: null, name: "Grasses", id: 11, image: null},
        {color: null, name: "Crops", id: 12, image: null},
        {color: null, name: "Shrubs", id: 13, image: null},
        {color: null, name: "Trees", id: 14, image: null},
        {color: null, name: "Roads/Parking Lots", id: 15, image: null},
        {color: null, name: "Buildings", id: 16, image: null},
        {color: null, name: "Water", id: 17, image: null},
        {color: null, name: "Unknown", id: 19, image: null}]}],
    archived: false},
  {id: 3,
    institution: 1,
    availability: "published",
    name: "Mongolia",
    description: "The land of yurt-dwelling pastoral nomads.",
    privacyLevel: "public",
    boundary: "{\"type\":\"Polygon\",\"coordinates\":[[[87,41.5],[87,52.5],[120.5,52.5],[120.5,41.5],[87,41.5]]]}",
    baseMapSource: "DigitalGlobeRecentImagery+Streets",
    plotDistribution: "random",
    numPlots: 3,
    plotSpacing: null,
    plotShape: "circle",
    plotSize: 400,
    sampleDistribution: "random",
    samplesPerPlot: 20,
    sampleResolution: null,
    sampleValues: [{id: 1,
      name: "Land Use",
      values: [{color: "#dd1919", name: "A", id: 33, image: ""},
        {color: "#81e315", name: "B", id: 34, image: ""},
        {color: "#ece91f", name: "C", id: 35, image: ""},
        {color: "#20e33e", name: "D", id: 36, image: ""},
        {color: "#1cd8ae", name: "E", id: 37, image: ""},
        {color: "#2149cb", name: "F", id: 38, image: ""},
        {color: "#7b17e4", name: "G", id: 39, image: ""},
        {color: "#e41b69", name: "H", id: 40, image: ""},
        {color: "#d62c3a", name: "I", id: 41, image: ""},
        {color: "#ad8787", name: "J", id: 42, image: ""},
        {color: "#c8d5e1", name: "K", id: 43, image: ""},
        {color: "#847d40", name: "L", id: 44, image: ""},
        {color: "#df0606", name: "M", id: 45, image: ""},
        {color: "#38182b", name: "N", id: 46, image: ""},
        {color: "#f2e2e2", name: "O", id: 47, image: ""}]}],
    archived: false},
  {id: 9,
    institution: 1,
    availability: "published",
    name: "FAO Regional Subset Collection",
    description: "",
    privacyLevel: "public",
    boundary: "{\"type\":\"Polygon\",\"coordinates\":[[[98.465659,6.082081],[98.465659,23.057802],[109.280806,23.057802],[109.280806,6.082081],[98.465659,6.082081]]]}",
    baseMapSource: "DigitalGlobeRecentImagery+Streets",
    plotDistribution: "random",
    numPlots: 3,
    plotSpacing: null,
    plotShape: "circle",
    plotSize: 78.986,
    sampleDistribution: "random",
    samplesPerPlot: 49,
    sampleResolution: null,
    sampleValues: [{id: 1,
      name: "Land Use",
      values: [{color: "#1EC61B", name: "Forest", id: 51, image: null},
        {color: "#aa3b3b", name: "Other land with tree cover", id: 52, image: null},
        {color: "#9CF135", name: "Other wooded land", id: 53, image: null},
        {color: "#1a9db2", name: "Inland water body", id: 54, image: null},
        {color: "#000000", name: "Other", id: 55, image: null}]}],
    archived: false},
  {id: 12,
    institution: 1,
    availability: "published",
    name: "Bing Maps Test",
    description: "",
    privacyLevel: "public",
    boundary: "{\"type\":\"Polygon\",\"coordinates\":[[[95.7568359375,16.6572436453608],[95.7568359375,17.7277586098523],[97.88818359375,17.7277586098523],[97.88818359375,16.6572436453608],[95.7568359375,16.6572436453608]]]}",
    baseMapSource: "BingAerialWithLabels",
    plotDistribution: "random",
    numPlots: 3,
    plotSpacing: null,
    plotShape: "circle",
    plotSize: 200,
    sampleDistribution: "gridded",
    samplesPerPlot: 69,
    sampleResolution: 20,
    sampleValues: [{id: 1,
      name: "Land Use",
      values: [{color: "#2acf2f", name: "Forest", id: 56, image: ""},
        {color: "#e96412", name: "Agriculture", id: 57, image: ""},
        {color: "#1ba7d1", name: "Water", id: 58, image: ""},
        {color: "#000000", name: "Unknown", id: 59, image: ""}]}],
    archived: false},
  {id: 14,
    institution: 1,
    availability: "published",
    name: "Heilongjiang",
    description: "",
    privacyLevel: "public",
    boundary: "{\"type\":\"Polygon\",\"coordinates\":[[[123.7939453125,46.1189415061071],[123.7939453125,49.8804776387425],[131.6162109375,49.8804776387425],[131.6162109375,46.1189415061071],[123.7939453125,46.1189415061071]]]}",
    baseMapSource: "BingAerialWithLabels",
    plotDistribution: "random",
    numPlots: 3,
    plotSpacing: null,
    plotShape: "circle",
    plotSize: 100,
    sampleDistribution: "random",
    samplesPerPlot: 20,
    sampleResolution: null,
    sampleValues: [{id: 1,
      name: "Land Use",
      values: [{color: "#d82a2a", name: "Type A", id: 63, image: ""},
        {color: "#4dd50c", name: "Type B", id: 64, image: ""}]}],
    archived: false},
  {id: 15,
    institution: 1,
    availability: "published",
    name: "Central Japan",
    description: "",
    privacyLevel: "public",
    boundary: "{\"type\":\"Polygon\",\"coordinates\":[[[136.93359375,34.9399851515604],[136.93359375,36.7916906190707],[141.064453125,36.7916906190707],[141.064453125,34.9399851515604],[136.93359375,34.9399851515604]]]}",
    baseMapSource: "DigitalGlobeRecentImagery+Streets",
    plotDistribution: "random",
    numPlots: 3,
    plotSpacing: null,
    plotShape: "circle",
    plotSize: 100,
    sampleDistribution: "gridded",
    samplesPerPlot: 16,
    sampleResolution: 20,
    sampleValues: [{id: 1,
      name: "Land Use",
      values: [{color: "#1e88f5", name: "Katakana", id: 65, image: ""},
        {color: "#c95b23", name: "Hiragana", id: 66, image: ""},
        {color: "#11dd55", name: "Kanji", id: 67, image: ""}]}],
    archived: false}]